.VERSION
AUTHORS.rst
CONTRIBUTING.rst
HISTORY.rst
LICENSE
MANIFEST.in
Pipfile
Pipfile.lock
README.rst
USAGE.rst
dev-requirements.txt
requirements.txt
setup.cfg
setup.py
commonutilslib/.VERSION
commonutilslib/AUTHORS.rst
commonutilslib/CONTRIBUTING.rst
commonutilslib/HISTORY.rst
commonutilslib/LICENSE
commonutilslib/Pipfile
commonutilslib/Pipfile.lock
commonutilslib/README.rst
commonutilslib/USAGE.rst
commonutilslib/__init__.py
commonutilslib/_version.py
commonutilslib/commonutilslib.py
commonutilslib/commonutilslibexceptions.py
commonutilslib/dev-requirements.txt
commonutilslib/requirements.txt
commonutilslib.egg-info/PKG-INFO
commonutilslib.egg-info/SOURCES.txt
commonutilslib.egg-info/dependency_links.txt
commonutilslib.egg-info/not-zip-safe
commonutilslib.egg-info/top_level.txt
docs/Makefile
docs/authors.rst
docs/commonutilslib.rst
docs/conf.py
docs/contributing.rst
docs/history.rst
docs/index.rst
docs/installation.rst
docs/modules.rst
docs/readme.rst
docs/usage.rst