Metadata-Version: 1.1
Name: commonutilslib
Version: 0.1.3
Summary: A library with some common utility methods for python like tempdir and Pushd
Home-page: https://github.com/schubergphilis/commonutilslib.git
Author: Costas Tyfoxylos
Author-email: ctyfoxylos@schubergphilis.com
License: MIT
Keywords: commonutilslib pushd tempdir recursive_dictionary hash_calculation
Platform: UNKNOWN
Classifier: Development Status :: 4 - Beta
Classifier: Intended Audience :: Developers
Classifier: License :: OSI Approved :: MIT License
Classifier: Natural Language :: English
Classifier: Programming Language :: Python :: 3.7
